<!-- Units are MPa, mm, s, and Kelvin -->
<materials>
  <!-- Nominally valid over 273 to 1073 K -->
  <!-- Source: MCM fit to ASME and collected data -->
  <material name="gr91_simple" type="smallstrain">
    <elastic type="isotropic">
      <youngs>
        <modulus>
          <interpolate type="piecewise">273.15 214750.0 288.741836735 213658.571429 304.333673469 212587.755102 319.925510204 211548.29932 335.517346939 210508.843537 351.109183673 209469.387755 366.701020408 208429.931973 382.292857143 207451.428571 397.884693878 206515.918367 413.476530612 205580.408163 429.068367347 204526.530612 444.660204082 203279.183673 460.252040816 202031.836735 475.843877551 200838.367347 491.435714286 199902.857143 507.02755102 198967.346939 522.619387755 198031.836735 538.21122449 197096.326531 553.803061224 196160.816327 569.394897959 195225.306122 584.986734694 194053.061224 600.578571429 192805.714286 616.170408163 191558.367347 631.762244898 190311.020408 647.354081633 189063.673469 662.945918367 187816.326531 678.537755102 186568.979592 694.129591837 185321.632653 709.721428571 184074.285714 725.313265306 182826.938776 740.905102041 181579.591837 756.496938776 180332.244898 772.08877551 179084.897959 787.680612245 177546.938776 803.27244898 175987.755102 818.864285714 174428.571429 834.456122449 172643.265306 850.047959184 170772.244898 865.639795918 168901.22449 881.231632653 166868.571429 896.823469388 164685.714286 912.415306122 162502.857143 928.007142857 160222.857143 943.598979592 157728.163265 959.190816327 155233.469388 974.782653061 152738.77551 990.374489796 150244.081633 1005.96632653 147749.387755 1021.55816327 145254.693878 1037.15 142760.0</interpolate>
        </modulus>
      </youngs>
      <poissons>
        <modulus>0.3</modulus>
      </poissons>
    </elastic>
    <plastic type="independent">
      <rule type="associative">
        <surface type="isoj2"/>
        <hardening type="isotropic">
          <isotropic type="combined">
            <models>
              <isotropic type="linear">
                <yield>0.0</yield>
                <harden>0.0</harden>
              </isotropic>
              <isotropic type="voce">
                <yield>
                  <interpolate type="piecewise">273.15 544.943357407 288.741836735 544.943357407 304.333673469 542.996414384 319.925510204 540.3414131 335.517346939 537.686411817 351.109183673 535.031410533 366.701020408 532.376409249 382.292857143 529.877093904 397.884693878 527.487592749 413.476530612 525.098091594 429.068367347 522.406253905 444.660204082 519.220252364 460.252040816 516.034250824 475.843877551 513.010155034 491.435714286 510.596363378 507.02755102 508.206862222 522.619387755 505.817361067 538.21122449 503.427859911 553.803061224 501.038358756 569.394897959 498.648857601 584.986734694 495.654683378 600.578571429 492.468681838 616.170408163 489.282680297 631.762244898 486.096678757 647.354081633 482.910677216 662.945918367 479.724675676 678.537755102 476.538674135 694.129591837 473.352672595 709.721428571 470.166671054 725.313265306 466.980669513 740.905102041 463.794667973 756.496938776 460.608666432 772.08877551 453.821786259 787.680612245 414.27227048 803.27244898 377.338204805 818.864285714 343.069789912 834.456122449 309.846458097 850.047959184 278.607892985 865.639795918 249.959976301 881.231632653 222.770622177 896.823469388 197.177070023 912.415306122 173.983601608 928.007142857 152.548460655 943.598979592 132.430042902 959.190816327 114.450557462 974.782653061 98.467587134 990.374489796 84.3173850937 1005.96632653 71.8435001449 1021.55816327 60.896942922 1037.15 51.336322533</interpolate>
                </yield>
                <r>
                  <interpolate type="piecewise">273.15 163.747950739 288.741836735 159.14967929 304.333673469 154.372498082 319.925510204 149.590441082 335.517346939 144.911479983 351.109183673 140.334603019 366.701020408 135.858785842 382.292857143 131.510749303 397.884693878 127.282526418 413.476530612 123.153611987 429.068367347 119.066391713 444.660204082 114.981332152 460.252040816 110.988571158 475.843877551 107.118646952 491.435714286 103.458713757 507.02755102 99.8955775525 522.619387755 96.4232225834 538.21122449 93.0403138683 553.803061224 89.7455140723 569.394897959 86.5374838622 584.986734694 83.2955508988 600.578571429 80.0999947945 616.170408163 76.9878012332 631.762244898 73.9580990551 647.354081633 71.0099968378 662.945918367 68.1425831091 678.537755102 65.3549265816 694.129591837 62.6460764123 709.721428571 60.0150624843 725.313265306 57.4608957147 740.905102041 54.9825683865 756.496938776 52.5790545064 772.08877551 50.2450408548 787.680612245 47.8568581304 803.27244898 45.52970684 818.864285714 43.2725759347 834.456122449 40.9972238083 850.047959184 38.7557851449 865.639795918 36.5912837804 881.231632653 34.4345637805 896.823469388 33.354946616 912.415306122 33.354946616 928.007142857 33.354946616 943.598979592 33.354946616 959.190816327 33.354946616 974.782653061 33.354946616 990.374489796 33.354946616 1005.96632653 33.354946616 1021.55816327 33.354946616 1037.15 33.354946616</interpolate>
                </r>
                <d>
                  <interpolate type="piecewise">273.15 329.783116884 288.741836735 339.311457108 304.333673469 348.561935581 319.925510204 357.945857192 335.517346939 367.687781506 351.109183673 377.804770726 366.701020408 388.314852957 382.292857143 399.270131108 397.884693878 410.673226902 413.476530612 422.518972433 429.068367347 434.782548279 444.660204082 447.483696307 460.252040816 460.737112829 475.843877551 474.584786942 491.435714286 489.06160792 507.02755102 504.135396913 522.619387755 519.834403292 538.21122449 536.190367776 553.803061224 553.236920644 569.394897959 571.009710215 584.986734694 589.67177175 600.578571429 609.25493837 616.170408163 629.782886767 631.762244898 651.313144016 647.354081633 673.907428061 662.945918367 697.632001623 678.537755102 722.558060037 694.129591837 748.762156636 709.721428571 776.326669758 725.313265306 805.340315927 740.905102041 835.898714295 756.496938776 868.105008086 772.08877551 902.101583253 787.680612245 939.03255793 803.27244898 978.361247842 818.864285714 1020.21457424 834.456122449 1065.87637804 850.047959184 1115.30177322 865.639795918 1168.3334103 881.231632653 1226.56793465 896.823469388 1249.70446834 912.415306122 1233.14003021 928.007142857 1215.79151415 943.598979592 1196.90764479 959.190816327 1177.97685835 974.782653061 1159.04607192 990.374489796 1140.11528548 1005.96632653 1121.18449905 1021.55816327 1102.25371262 1037.15 1083.32292618</interpolate>
                </d>
              </isotropic>
            </models>
          </isotropic>
        </hardening>
      </rule>
    </plastic>
    <creep type="j2">
      <scalarmodel type="regionkm">
        <cuts>0.0</cuts>
        <As>-0.115015876494</As>
        <Bs>-0.191743605543</Bs>
        <kboltz>1.38064e-20</kboltz>
        <b>2.474e-07</b>
        <eps0>10000000000.0</eps0>
        <elastic type="isotropic">
          <youngs>
            <modulus>
              <interpolate type="piecewise">273.15 214750.0 288.741836735 213658.571429 304.333673469 212587.755102 319.925510204 211548.29932 335.517346939 210508.843537 351.109183673 209469.387755 366.701020408 208429.931973 382.292857143 207451.428571 397.884693878 206515.918367 413.476530612 205580.408163 429.068367347 204526.530612 444.660204082 203279.183673 460.252040816 202031.836735 475.843877551 200838.367347 491.435714286 199902.857143 507.02755102 198967.346939 522.619387755 198031.836735 538.21122449 197096.326531 553.803061224 196160.816327 569.394897959 195225.306122 584.986734694 194053.061224 600.578571429 192805.714286 616.170408163 191558.367347 631.762244898 190311.020408 647.354081633 189063.673469 662.945918367 187816.326531 678.537755102 186568.979592 694.129591837 185321.632653 709.721428571 184074.285714 725.313265306 182826.938776 740.905102041 181579.591837 756.496938776 180332.244898 772.08877551 179084.897959 787.680612245 177546.938776 803.27244898 175987.755102 818.864285714 174428.571429 834.456122449 172643.265306 850.047959184 170772.244898 865.639795918 168901.22449 881.231632653 166868.571429 896.823469388 164685.714286 912.415306122 162502.857143 928.007142857 160222.857143 943.598979592 157728.163265 959.190816327 155233.469388 974.782653061 152738.77551 990.374489796 150244.081633 1005.96632653 147749.387755 1021.55816327 145254.693878 1037.15 142760.0</interpolate>
            </modulus>
          </youngs>
          <poissons>
            <modulus>0.3</modulus>
          </poissons>
        </elastic>
      </scalarmodel>
    </creep>
    <alpha>
      <value>
        <interpolate type="piecewise">273.15 1.03e-05 288.741836735 1.04559183673e-05 304.333673469 1.06118367347e-05 319.925510204 1.0767755102e-05 335.517346939 1.08989387755e-05 351.109183673 1.10236734694e-05 366.701020408 1.11484081633e-05 382.292857143 1.12731428571e-05 397.884693878 1.1397877551e-05 413.476530612 1.15226122449e-05 429.068367347 1.16473469388e-05 444.660204082 1.17720816327e-05 460.252040816 1.18968163265e-05 475.843877551 1.20215510204e-05 491.435714286 1.21462857143e-05 507.02755102 1.22710204082e-05 522.619387755 1.2395755102e-05 538.21122449 1.2460244898e-05 553.803061224 1.25452244898e-05 569.394897959 1.26699591837e-05 584.986734694 1.27473469388e-05 600.578571429 1.28194285714e-05 616.170408163 1.29441632653e-05 631.762244898 1.30344489796e-05 647.354081633 1.30968163265e-05 662.945918367 1.32183673469e-05 678.537755102 1.33215510204e-05 694.129591837 1.33839183673e-05 709.721428571 1.34925714286e-05 725.313265306 1.36086530612e-05 740.905102041 1.36710204082e-05 756.496938776 1.37333877551e-05 772.08877551 1.3795755102e-05 787.680612245 1.3916244898e-05 803.27244898 1.40409795918e-05 818.864285714 1.41657142857e-05 834.456122449 1.42904489796e-05 850.047959184 1.44151836735e-05 865.639795918 1.45399183673e-05 881.231632653 1.46969795918e-05 896.823469388 1.48840816327e-05 912.415306122 1.50711836735e-05 928.007142857 1.52582857143e-05 943.598979592 1.54453877551e-05 959.190816327 1.57208163265e-05 974.782653061 1.60326530612e-05 990.374489796 1.63444897959e-05 1005.96632653 1.66875918367e-05 1021.55816327 1.70617959184e-05 1037.15 1.7548e-05</interpolate>
      </value>
    </alpha>
  </material>

  <!-- Nominally valid over 273 to 1073 K -->
  <!-- Source: MCM fit to ASME and collected data -->
  <material name="gr91_elastic_creep" type="smallstrain">
    <elastic type="isotropic">
      <youngs>
        <modulus>
          <interpolate type="piecewise">273.15 214750.0 288.741836735 213658.571429 304.333673469 212587.755102 319.925510204 211548.29932 335.517346939 210508.843537 351.109183673 209469.387755 366.701020408 208429.931973 382.292857143 207451.428571 397.884693878 206515.918367 413.476530612 205580.408163 429.068367347 204526.530612 444.660204082 203279.183673 460.252040816 202031.836735 475.843877551 200838.367347 491.435714286 199902.857143 507.02755102 198967.346939 522.619387755 198031.836735 538.21122449 197096.326531 553.803061224 196160.816327 569.394897959 195225.306122 584.986734694 194053.061224 600.578571429 192805.714286 616.170408163 191558.367347 631.762244898 190311.020408 647.354081633 189063.673469 662.945918367 187816.326531 678.537755102 186568.979592 694.129591837 185321.632653 709.721428571 184074.285714 725.313265306 182826.938776 740.905102041 181579.591837 756.496938776 180332.244898 772.08877551 179084.897959 787.680612245 177546.938776 803.27244898 175987.755102 818.864285714 174428.571429 834.456122449 172643.265306 850.047959184 170772.244898 865.639795918 168901.22449 881.231632653 166868.571429 896.823469388 164685.714286 912.415306122 162502.857143 928.007142857 160222.857143 943.598979592 157728.163265 959.190816327 155233.469388 974.782653061 152738.77551 990.374489796 150244.081633 1005.96632653 147749.387755 1021.55816327 145254.693878 1037.15 142760.0</interpolate>
        </modulus>
      </youngs>
      <poissons>
        <modulus>0.3</modulus>
      </poissons>
    </elastic>
    <creep type="j2">
      <scalarmodel type="regionkm">
        <cuts>0.0</cuts>
        <As>-0.115015876494</As>
        <Bs>-0.191743605543</Bs>
        <kboltz>1.38064e-20</kboltz>
        <b>2.474e-07</b>
        <eps0>10000000000.0</eps0>
        <elastic type="isotropic">
          <youngs>
            <modulus>
              <interpolate type="piecewise">273.15 214750.0 288.741836735 213658.571429 304.333673469 212587.755102 319.925510204 211548.29932 335.517346939 210508.843537 351.109183673 209469.387755 366.701020408 208429.931973 382.292857143 207451.428571 397.884693878 206515.918367 413.476530612 205580.408163 429.068367347 204526.530612 444.660204082 203279.183673 460.252040816 202031.836735 475.843877551 200838.367347 491.435714286 199902.857143 507.02755102 198967.346939 522.619387755 198031.836735 538.21122449 197096.326531 553.803061224 196160.816327 569.394897959 195225.306122 584.986734694 194053.061224 600.578571429 192805.714286 616.170408163 191558.367347 631.762244898 190311.020408 647.354081633 189063.673469 662.945918367 187816.326531 678.537755102 186568.979592 694.129591837 185321.632653 709.721428571 184074.285714 725.313265306 182826.938776 740.905102041 181579.591837 756.496938776 180332.244898 772.08877551 179084.897959 787.680612245 177546.938776 803.27244898 175987.755102 818.864285714 174428.571429 834.456122449 172643.265306 850.047959184 170772.244898 865.639795918 168901.22449 881.231632653 166868.571429 896.823469388 164685.714286 912.415306122 162502.857143 928.007142857 160222.857143 943.598979592 157728.163265 959.190816327 155233.469388 974.782653061 152738.77551 990.374489796 150244.081633 1005.96632653 147749.387755 1021.55816327 145254.693878 1037.15 142760.0</interpolate>
            </modulus>
          </youngs>
          <poissons>
            <modulus>0.3</modulus>
          </poissons>
        </elastic>
      </scalarmodel>
    </creep>
    <alpha>
      <value>
        <interpolate type="piecewise">273.15 1.03e-05 288.741836735 1.04559183673e-05 304.333673469 1.06118367347e-05 319.925510204 1.0767755102e-05 335.517346939 1.08989387755e-05 351.109183673 1.10236734694e-05 366.701020408 1.11484081633e-05 382.292857143 1.12731428571e-05 397.884693878 1.1397877551e-05 413.476530612 1.15226122449e-05 429.068367347 1.16473469388e-05 444.660204082 1.17720816327e-05 460.252040816 1.18968163265e-05 475.843877551 1.20215510204e-05 491.435714286 1.21462857143e-05 507.02755102 1.22710204082e-05 522.619387755 1.2395755102e-05 538.21122449 1.2460244898e-05 553.803061224 1.25452244898e-05 569.394897959 1.26699591837e-05 584.986734694 1.27473469388e-05 600.578571429 1.28194285714e-05 616.170408163 1.29441632653e-05 631.762244898 1.30344489796e-05 647.354081633 1.30968163265e-05 662.945918367 1.32183673469e-05 678.537755102 1.33215510204e-05 694.129591837 1.33839183673e-05 709.721428571 1.34925714286e-05 725.313265306 1.36086530612e-05 740.905102041 1.36710204082e-05 756.496938776 1.37333877551e-05 772.08877551 1.3795755102e-05 787.680612245 1.3916244898e-05 803.27244898 1.40409795918e-05 818.864285714 1.41657142857e-05 834.456122449 1.42904489796e-05 850.047959184 1.44151836735e-05 865.639795918 1.45399183673e-05 881.231632653 1.46969795918e-05 896.823469388 1.48840816327e-05 912.415306122 1.50711836735e-05 928.007142857 1.52582857143e-05 943.598979592 1.54453877551e-05 959.190816327 1.57208163265e-05 974.782653061 1.60326530612e-05 990.374489796 1.63444897959e-05 1005.96632653 1.66875918367e-05 1021.55816327 1.70617959184e-05 1037.15 1.7548e-05</interpolate>
      </value>
    </alpha>
  </material>

  <!-- Nominally valid over 273 to 1073 K -->
  <!-- Source: MCM fit to ASME and collected data -->
  <material name="gr91_elastic" type="smallstrain">
    <elastic type="isotropic">
      <youngs>
        <modulus>
          <interpolate type="piecewise">273.15 214750.0 288.741836735 213658.571429 304.333673469 212587.755102 319.925510204 211548.29932 335.517346939 210508.843537 351.109183673 209469.387755 366.701020408 208429.931973 382.292857143 207451.428571 397.884693878 206515.918367 413.476530612 205580.408163 429.068367347 204526.530612 444.660204082 203279.183673 460.252040816 202031.836735 475.843877551 200838.367347 491.435714286 199902.857143 507.02755102 198967.346939 522.619387755 198031.836735 538.21122449 197096.326531 553.803061224 196160.816327 569.394897959 195225.306122 584.986734694 194053.061224 600.578571429 192805.714286 616.170408163 191558.367347 631.762244898 190311.020408 647.354081633 189063.673469 662.945918367 187816.326531 678.537755102 186568.979592 694.129591837 185321.632653 709.721428571 184074.285714 725.313265306 182826.938776 740.905102041 181579.591837 756.496938776 180332.244898 772.08877551 179084.897959 787.680612245 177546.938776 803.27244898 175987.755102 818.864285714 174428.571429 834.456122449 172643.265306 850.047959184 170772.244898 865.639795918 168901.22449 881.231632653 166868.571429 896.823469388 164685.714286 912.415306122 162502.857143 928.007142857 160222.857143 943.598979592 157728.163265 959.190816327 155233.469388 974.782653061 152738.77551 990.374489796 150244.081633 1005.96632653 147749.387755 1021.55816327 145254.693878 1037.15 142760.0</interpolate>
        </modulus>
      </youngs>
      <poissons>
        <modulus>0.3</modulus>
      </poissons>
    </elastic>
    <alpha>
      <value>
        <interpolate type="piecewise">273.15 1.03e-05 288.741836735 1.04559183673e-05 304.333673469 1.06118367347e-05 319.925510204 1.0767755102e-05 335.517346939 1.08989387755e-05 351.109183673 1.10236734694e-05 366.701020408 1.11484081633e-05 382.292857143 1.12731428571e-05 397.884693878 1.1397877551e-05 413.476530612 1.15226122449e-05 429.068367347 1.16473469388e-05 444.660204082 1.17720816327e-05 460.252040816 1.18968163265e-05 475.843877551 1.20215510204e-05 491.435714286 1.21462857143e-05 507.02755102 1.22710204082e-05 522.619387755 1.2395755102e-05 538.21122449 1.2460244898e-05 553.803061224 1.25452244898e-05 569.394897959 1.26699591837e-05 584.986734694 1.27473469388e-05 600.578571429 1.28194285714e-05 616.170408163 1.29441632653e-05 631.762244898 1.30344489796e-05 647.354081633 1.30968163265e-05 662.945918367 1.32183673469e-05 678.537755102 1.33215510204e-05 694.129591837 1.33839183673e-05 709.721428571 1.34925714286e-05 725.313265306 1.36086530612e-05 740.905102041 1.36710204082e-05 756.496938776 1.37333877551e-05 772.08877551 1.3795755102e-05 787.680612245 1.3916244898e-05 803.27244898 1.40409795918e-05 818.864285714 1.41657142857e-05 834.456122449 1.42904489796e-05 850.047959184 1.44151836735e-05 865.639795918 1.45399183673e-05 881.231632653 1.46969795918e-05 896.823469388 1.48840816327e-05 912.415306122 1.50711836735e-05 928.007142857 1.52582857143e-05 943.598979592 1.54453877551e-05 959.190816327 1.57208163265e-05 974.782653061 1.60326530612e-05 990.374489796 1.63444897959e-05 1005.96632653 1.66875918367e-05 1021.55816327 1.70617959184e-05 1037.15 1.7548e-05</interpolate>
      </value>
    </alpha>
  </material>

  <!-- Valid over 473 to 873 K -->
  <!-- Sources: 
          Yaguchi and Takahashi, IJP, 2000.
          ASME thermal expansion coefficients
  -->
  <material name="yaguchi" type="smallstrain">
    <elastic type="isotropic">
      <youngs>
        <modulus>
          <interpolate type="polynomial">-3.077e-1, 3.003e2, 1.269e5</interpolate>
        </modulus>
      </youngs>
      <poissons>
        <modulus>
          0.3
        </modulus>
      </poissons>
    </elastic>

    <plastic type="dependent">
      <rule type="yaguchigr91">
      </rule>
    </plastic>
    <alpha>
      <value>
        <interpolate type="piecewise">
          293.15	0.0000105
          323.15	0.0000108
          348.15	0.000011
          373.15	0.0000112
          398.15	0.0000114
          423.15	0.0000116
          448.15	0.0000118
          473.15	0.000012
          498.15	0.0000122
          523.15	0.0000124
          548.15	0.0000125
          573.15	0.0000127
          598.15	0.0000128
          623.15	0.000013
          648.15	0.0000131
          673.15	0.0000133
          698.15	0.0000134
          723.15	0.0000136
          748.15	0.0000137
          773.15	0.0000138
          798.15	0.000014
          823.15	0.0000142
          848.15	0.0000144
          873.15	0.0000146
          898.15	0.0000149
          923.15	0.0000152
          948.15	0.0000155
          973.15	0.000016
          998.15	0.0000165
          1023.15	0.0000171
          1048.15	0.0000179
          1073.15	0.0000188
          1098.15	0.0000199
        </interpolate>
      </value>
    </alpha>
  </material>
  <!-- Valid over 773 to 873 K, but paper does not provide explicit interpolation -->
  <!-- Sources:
          Koo & Kwon, IJPVP, 2011.
          ASME thermal expansion coefficients
  -->
  <material name="koo" type="smallstrain">
    <elastic type="isotropic">
      <youngs>
        <modulus>
          <interpolate type="piecewise">
            773.15 157000.0
            823.15 155000.0
            873.15 150000.0
          </interpolate>
        </modulus>
      </youngs>
      <poissons>
        <modulus>
          0.3
        </modulus>
      </poissons>
    </elastic>

    <plastic type="dependent">
      <rule type="chaboche">
        <surface type="isokinj2"></surface>
        <hardening type="chaboche">
          <isotropic type="voce">
            <yield>
              0.0
            </yield>
            <r>
              <interpolate type="piecewise">
                773.15 -80.0
                823.15 -100.0
                873.15 -110.0
              </interpolate>
            </r>
            <d>
              <interpolate type="piecewise">
                773.15 3.0
                823.15 4.0
                873.15 5.0
              </interpolate>
            </d>
          </isotropic>
          <c>
            <interpolate type="piecewise">
              773.15 135.0e3
              823.15 135.0e3
              873.15 135.0e3
            </interpolate>
            <interpolate type="piecewise">            
              773.15 123.0e3
              823.15 107.0e3
              873.15 61.0e3
            </interpolate>
            <interpolate type="piecewise">            
              773.15 4.0e3
              823.15 6.0e3
              873.15 11.0e3
            </interpolate>
          </c>
          <gammamodels>
            <gammamodel type="constant">
              <g><interpolate type="piecewise">            
                773.15 100.0e3
                823.15 100.0e3
                873.15 50.0e3
              </interpolate></g>
            </gammamodel>
            <gammamodel type="constant">
              <g><interpolate type="piecewise">            
                773.15 0.85e3
                823.15 1.0e3
                873.15 1.1e3
              </interpolate></g>
            </gammamodel>
            <gammamodel type="constant">
              <g><interpolate type="piecewise">            
                773.15 1.0
                823.15 1.0
                873.15 1.0
              </interpolate></g>
            </gammamodel>
          </gammamodels>
        </hardening>
        <fluidity type="constant">
          <eta>
            <interpolate type="piecewise">            
              773.15 701
              823.15 1265
              873.15 3075
            </interpolate>
          </eta>
        </fluidity>
        <n>
          <interpolate type="piecewise">            
            773.15 10.5
            823.15 6.0
            873.15 3.6
          </interpolate>
        </n>
      </rule>
    </plastic>
    <alpha>
      <value>
        <interpolate type="piecewise">
          293.15	0.0000105
          323.15	0.0000108
          348.15	0.000011
          373.15	0.0000112
          398.15	0.0000114
          423.15	0.0000116
          448.15	0.0000118
          473.15	0.000012
          498.15	0.0000122
          523.15	0.0000124
          548.15	0.0000125
          573.15	0.0000127
          598.15	0.0000128
          623.15	0.000013
          648.15	0.0000131
          673.15	0.0000133
          698.15	0.0000134
          723.15	0.0000136
          748.15	0.0000137
          773.15	0.0000138
          798.15	0.000014
          823.15	0.0000142
          848.15	0.0000144
          873.15	0.0000146
          898.15	0.0000149
          923.15	0.0000152
          948.15	0.0000155
          973.15	0.000016
          998.15	0.0000165
          1023.15	0.0000171
          1048.15	0.0000179
          1073.15	0.0000188
          1098.15	0.0000199
        </interpolate>
      </value>
    </alpha>
  </material>

  <!-- Valid over 293.15 to 923.15 -->
  <!-- Sources:
          ANL research to be published
          ASME youngs modulus
          ASME poissons ratio
          ASME thermal expansion coefficients
  -->
  <material name="gr91_unified" type="kmregion">
    <models>
      <model>
        <elastic type="isotropic">
          <youngs>
            <modulus>
              <interpolate type="piecewise">273.15 214750.0 288.741836735 213658.571429 304.333673469 212587.755102 319.925510204 211548.29932 335.517346939 210508.843537 351.109183673 209469.387755 366.701020408 208429.931973 382.292857143 207451.428571 397.884693878 206515.918367 413.476530612 205580.408163 429.068367347 204526.530612 444.660204082 203279.183673 460.252040816 202031.836735 475.843877551 200838.367347 491.435714286 199902.857143 507.02755102 198967.346939 522.619387755 198031.836735 538.21122449 197096.326531 553.803061224 196160.816327 569.394897959 195225.306122 584.986734694 194053.061224 600.578571429 192805.714286 616.170408163 191558.367347 631.762244898 190311.020408 647.354081633 189063.673469 662.945918367 187816.326531 678.537755102 186568.979592 694.129591837 185321.632653 709.721428571 184074.285714 725.313265306 182826.938776 740.905102041 181579.591837 756.496938776 180332.244898 772.08877551 179084.897959 787.680612245 177546.938776 803.27244898 175987.755102 818.864285714 174428.571429 834.456122449 172643.265306 850.047959184 170772.244898 865.639795918 168901.22449 881.231632653 166868.571429 896.823469388 164685.714286 912.415306122 162502.857143 928.007142857 160222.857143 943.598979592 157728.163265 959.190816327 155233.469388 974.782653061 152738.77551 990.374489796 150244.081633 1005.96632653 147749.387755 1021.55816327 145254.693878 1037.15 142760.0</interpolate>
            </modulus>
          </youngs>
          <poissons>
            <modulus>0.3</modulus>
          </poissons>
        </elastic>

        <plastic type="independent">
          <rule type="nonassociative_hardening">
            <surface type="isokinj2i1">
              <h><interpolate type="piecewise">298.15 0.0003575761 773.15 0.0007792597 823.15 0.0009947043 873.15 0.0006315028 923.15 3.64E-05</interpolate></h>
              <l><interpolate type="piecewise">298.15 0.001 773.15 1.7 823.15 1.0158977049 873.15 1.6521253158 923.15 1.5</interpolate></l>
            </surface>
            <hardening type="chaboche">
              <isotropic type="voce">
                <yield><interpolate type="piecewise">283.15 488.06737827 294.42118644 486.26837388 305.69237288 484.52669545 316.96355932 482.81335794 328.23474576 481.10002042 339.5059322 479.38668291 350.77711864 477.6733454 362.04830508 475.96000789 373.31949153 474.24924682 384.59067797 472.70724306 395.86186441 471.1652393 407.13305085 469.62323554 418.40423729 468.08123178 429.67542373 466.24164835 440.94661017 464.18564333 452.21779661 462.12963832 463.48898305 460.07363331 474.76016949 458.09105704 486.03135593 456.54905328 497.30254237 455.00704952 508.57372881 453.46504576 519.84491525 451.923042 531.11610169 450.38103824 542.38728814 448.83903448 553.65847458 447.29703072 564.92966102 445.75502696 576.20084746 444.07389504 587.4720339 442.01789002 598.74322034 439.96188501 610.01440678 437.90588 621.28559322 435.84987498 632.55677966 433.79386997 643.8279661 431.73786495 655.09915254 429.68185994 666.37033898 427.62585492 677.64152542 425.56984991 688.91271186 423.5138449 700.18389831 421.45783988 711.45508475 419.40183487 722.72627119 417.34582985 733.99745763 415.28982484 745.26864407 413.23381982 756.53983051 411.17781481 767.81101695 409.1218098 779.08220339 406.79527781 790.35338983 404.22527154 801.62457627 401.65526527 812.89576271 399.085259 824.16694915 396.46887668 835.43813559 393.38486916 846.70932203 390.30086164 857.98050847 387.21685412 869.25169492 384.1328466 880.52288136 380.71261269 891.7940678 377.11460392 903.06525424 373.51659514 914.33644068 369.91858637 925.60762712 366.20850213 936.87881356 362.0964921 948.15 357.98448208</interpolate></yield>
                <r><interpolate type="piecewise">298.15 -100 773.15 -79.979442587 823.15 -100 873.15 -100 923.15 -130</interpolate></r>
                <d><interpolate type="piecewise">298.15 2 773.15 1.6101477038 823.15 0.8099330475 873.15 2 923.15 4.5</interpolate></d>
              </isotropic>
              <c>
                <interpolate type="piecewise">298.15 27000 773.15 40121.8216 823.15 27500 873.15 27500 923.15 27500</interpolate>
                <interpolate type="piecewise">298.15 6992.272591 773.15 1 823.15 1 873.15 0 923.15 1</interpolate>
              </c>
              <gammamodels>
                <gammamodel type="constant">
                  <g><interpolate type="piecewise">298.15 350 773.15 363.58899 823.15 302.6169796 873.15 350 923.15 350</interpolate></g>
                </gammamodel>
                <gammamodel type="constant">
                  <g><interpolate type="piecewise">298.15 92 773.15 0 823.15 0 873.15 1048.2 923.15 0</interpolate></g>
                </gammamodel>
              </gammamodels>
              <A>
                <interpolate type="piecewise">298.15 1.38E-15 773.15 6.87E-16 823.15 1.27E-15 873.15 1.00E-15 923.15 8.43E-16</interpolate>
                <interpolate type="piecewise">298.15 2.32E-16 773.15 0 823.15 0 873.15 0 923.15 0</interpolate>
              </A>
              <a>
                <interpolate type="piecewise">298.15 3.3220207429 773.15 2.6937964995 823.15 4.185022822 873.15 4.0356999099 923.15 5.917262413</interpolate>
                <interpolate type="piecewise">298.15 3.4480651795 773.15 5.161053833 823.15 5 873.15 9.841218345 923.15 5.630725081</interpolate>
              </a>
            </hardening>
          </rule>
        </plastic>
      </model>

      <model>
        <elastic type="isotropic">
          <youngs>
            <modulus>
              <interpolate type="piecewise">273.15 214750.0 288.741836735 213658.571429 304.333673469 212587.755102 319.925510204 211548.29932 335.517346939 210508.843537 351.109183673 209469.387755 366.701020408 208429.931973 382.292857143 207451.428571 397.884693878 206515.918367 413.476530612 205580.408163 429.068367347 204526.530612 444.660204082 203279.183673 460.252040816 202031.836735 475.843877551 200838.367347 491.435714286 199902.857143 507.02755102 198967.346939 522.619387755 198031.836735 538.21122449 197096.326531 553.803061224 196160.816327 569.394897959 195225.306122 584.986734694 194053.061224 600.578571429 192805.714286 616.170408163 191558.367347 631.762244898 190311.020408 647.354081633 189063.673469 662.945918367 187816.326531 678.537755102 186568.979592 694.129591837 185321.632653 709.721428571 184074.285714 725.313265306 182826.938776 740.905102041 181579.591837 756.496938776 180332.244898 772.08877551 179084.897959 787.680612245 177546.938776 803.27244898 175987.755102 818.864285714 174428.571429 834.456122449 172643.265306 850.047959184 170772.244898 865.639795918 168901.22449 881.231632653 166868.571429 896.823469388 164685.714286 912.415306122 162502.857143 928.007142857 160222.857143 943.598979592 157728.163265 959.190816327 155233.469388 974.782653061 152738.77551 990.374489796 150244.081633 1005.96632653 147749.387755 1021.55816327 145254.693878 1037.15 142760.0</interpolate>
            </modulus>
          </youngs>
          <poissons>
            <modulus>0.3</modulus>
          </poissons>
        </elastic>

        <plastic type="dependent">
          <rule type="chaboche">
            <n><interpolate type="piecewise">283.15 33.1494351 294.42118644 31.76288068 305.69237288 30.48218004 316.96355932 29.29428207 328.23474576 28.18796609 339.5059322 27.1551068 350.77711864 26.18862329 362.04830508 25.28231636 373.31949153 24.43086822 384.59067797 23.63776554 395.86186441 22.88982612 407.13305085 22.18329904 418.40423729 21.51483753 429.67542373 20.86812688 440.94661017 20.24503877 452.21779661 19.65301067 463.48898305 19.0897766 474.76016949 18.55626022 486.03135593 18.06492135 497.30254237 17.59585453 508.57372881 17.14757894 519.84491525 16.71874222 531.11610169 16.30810679 542.38728814 15.91453794 553.65847458 15.53699337 564.92966102 15.17451394 576.20084746 14.821572 587.4720339 14.46990124 598.74322034 14.13147069 610.01440678 13.80554646 621.28559322 13.49144787 632.55677966 13.18854279 643.8279661 12.89624334 655.09915254 12.61400209 666.37033898 12.34130867 677.64152542 12.07768665 688.91271186 11.82269078 700.18389831 11.57590448 711.45508475 11.33693758 722.72627119 11.10542424 733.99745763 10.88102108 745.26864407 10.66340552 756.53983051 10.45227418 767.81101695 10.2473415 779.08220339 10.04166054 790.35338983 9.83592159 801.62457627 9.6359682 812.89576271 9.4415597 824.16694915 9.25138645 835.43813559 9.05558002 846.70932203 8.86498665 857.98050847 8.67940088 869.25169492 8.49862791 880.52288136 8.31513943 891.7940678 8.13245537 903.06525424 7.95433149 914.33644068 7.78059914 925.60762712 7.60876928 936.87881356 7.43282344 948.15 7.26106073</interpolate></n>
            <fluidity type="constant">
              <eta><interpolate type="piecewise">283.15 7169.96337262 294.42118644 6930.18042403 305.69237288 6698.20764034 316.96355932 6473.17209407 328.23474576 6254.25348455 339.5059322 6041.32958412 350.77711864 5834.27953565 362.04830508 5632.98385649 373.31949153 5437.38182238 384.59067797 5250.99793298 395.86186441 5069.89948534 407.13305085 4893.97132965 418.40423729 4723.09993022 429.67542373 4551.06244 440.94661017 4379.70590457 452.21779661 4213.44521977 463.48898305 4052.17476844 474.76016949 3897.18969073 486.03135593 3755.17220152 497.30254237 3617.46109376 508.57372881 3483.95496717 519.84491525 3354.55400184 531.11610169 3229.15995099 542.38728814 3107.67613345 553.65847458 2990.00742589 564.92966102 2876.06025483 576.20084746 2763.53137567 587.4720339 2648.81452107 598.74322034 2537.9090001 610.01440678 2430.72397637 621.28559322 2327.16971692 632.55677966 2227.1576017 643.8279661 2130.60013268 655.09915254 2037.41094265 666.37033898 1947.50480361 677.64152542 1860.79763485 688.91271186 1777.20651065 700.18389831 1696.64966757 711.45508475 1619.0465114 722.72627119 1544.31762367 733.99745763 1472.38476775 745.26864407 1403.1708946 756.53983051 1336.60014802 767.81101695 1272.5978695 779.08220339 1208.44279018 790.35338983 1144.57257182 801.62457627 1083.36911674 812.89576271 1024.75505637 824.16694915 968.25880866 835.43813559 910.39020948 846.70932203 855.19991271 857.98050847 802.60602511 869.25169492 752.52743798 880.52288136 702.54319529 891.7940678 653.93388458 903.06525424 607.9035104 914.33644068 564.36426711 925.60762712 522.58489043 936.87881356 480.99656152 948.15 441.93293904</interpolate></eta>
            </fluidity>
            <surface type="isokinj2i1">
              <h><interpolate type="piecewise">298.15 0.0003575761 773.15 0.0007792597 823.15 0.0009947043 873.15 0.0006315028 923.15 3.64E-05</interpolate></h>
              <l><interpolate type="piecewise">298.15 0.001 773.15 1.7 823.15 1.0158977049 873.15 1.6521253158 923.15 1.5</interpolate></l>
            </surface>
            <hardening type="chaboche">
              <isotropic type="voce">
                <yield>0.0</yield>
                <r><interpolate type="piecewise">298.15 -100 773.15 -79.979442587 823.15 -100 873.15 -100 923.15 -130</interpolate></r>
                <d><interpolate type="piecewise">298.15 2 773.15 1.6101477038 823.15 0.8099330475 873.15 2 923.15 4.5</interpolate></d>
              </isotropic>
              <c>
                <interpolate type="piecewise">298.15 27000 773.15 40121.8216 823.15 27500 873.15 27500 923.15 27500</interpolate>
                <interpolate type="piecewise">298.15 6992.272591 773.15 1 823.15 1 873.15 0 923.15 1</interpolate>
              </c>
              <gammamodels>
                <gammamodel type="constant">
                  <g><interpolate type="piecewise">298.15 350 773.15 363.58899 823.15 302.6169796 873.15 350 923.15 350</interpolate></g>
                </gammamodel>
                <gammamodel type="constant">
                  <g><interpolate type="piecewise">298.15 92 773.15 0 823.15 0 873.15 1048.2 923.15 0</interpolate></g>
                </gammamodel>
              </gammamodels>
              <A>
                <interpolate type="piecewise">298.15 1.38E-15 773.15 6.87E-16 823.15 1.27E-15 873.15 1.00E-15 923.15 8.43E-16</interpolate>
                <interpolate type="piecewise">298.15 2.32E-16 773.15 0 823.15 0 873.15 0 923.15 0</interpolate>
              </A>
              <a>
                <interpolate type="piecewise">298.15 3.3220207429 773.15 2.6937964995 823.15 4.185022822 873.15 4.0356999099 923.15 5.917262413</interpolate>
                <interpolate type="piecewise">298.15 3.4480651795 773.15 5.161053833 823.15 5 873.15 9.841218345 923.15 5.630725081</interpolate>
              </a>
            </hardening>
          </rule>
        </plastic>
      </model>
    </models>

    <gcut>0.349</gcut>

    <elastic type="isotropic">
      <youngs>
        <modulus>
          <interpolate type="piecewise">273.15 214750.0 288.741836735 213658.571429 304.333673469 212587.755102 319.925510204 211548.29932 335.517346939 210508.843537 351.109183673 209469.387755 366.701020408 208429.931973 382.292857143 207451.428571 397.884693878 206515.918367 413.476530612 205580.408163 429.068367347 204526.530612 444.660204082 203279.183673 460.252040816 202031.836735 475.843877551 200838.367347 491.435714286 199902.857143 507.02755102 198967.346939 522.619387755 198031.836735 538.21122449 197096.326531 553.803061224 196160.816327 569.394897959 195225.306122 584.986734694 194053.061224 600.578571429 192805.714286 616.170408163 191558.367347 631.762244898 190311.020408 647.354081633 189063.673469 662.945918367 187816.326531 678.537755102 186568.979592 694.129591837 185321.632653 709.721428571 184074.285714 725.313265306 182826.938776 740.905102041 181579.591837 756.496938776 180332.244898 772.08877551 179084.897959 787.680612245 177546.938776 803.27244898 175987.755102 818.864285714 174428.571429 834.456122449 172643.265306 850.047959184 170772.244898 865.639795918 168901.22449 881.231632653 166868.571429 896.823469388 164685.714286 912.415306122 162502.857143 928.007142857 160222.857143 943.598979592 157728.163265 959.190816327 155233.469388 974.782653061 152738.77551 990.374489796 150244.081633 1005.96632653 147749.387755 1021.55816327 145254.693878 1037.15 142760.0</interpolate>
        </modulus>
      </youngs>
      <poissons>
        <modulus>0.3</modulus>
      </poissons>
    </elastic>

    <kboltz>1.38064e-20</kboltz>
    <burgers>2.48e-07</burgers>
    <refrate>1.0e10</refrate>

    <alpha>
      <value>
        <interpolate type="piecewise">273.15 1.03e-05 288.741836735 1.04559183673e-05 304.333673469 1.06118367347e-05 319.925510204 1.0767755102e-05 335.517346939 1.08989387755e-05 351.109183673 1.10236734694e-05 366.701020408 1.11484081633e-05 382.292857143 1.12731428571e-05 397.884693878 1.1397877551e-05 413.476530612 1.15226122449e-05 429.068367347 1.16473469388e-05 444.660204082 1.17720816327e-05 460.252040816 1.18968163265e-05 475.843877551 1.20215510204e-05 491.435714286 1.21462857143e-05 507.02755102 1.22710204082e-05 522.619387755 1.2395755102e-05 538.21122449 1.2460244898e-05 553.803061224 1.25452244898e-05 569.394897959 1.26699591837e-05 584.986734694 1.27473469388e-05 600.578571429 1.28194285714e-05 616.170408163 1.29441632653e-05 631.762244898 1.30344489796e-05 647.354081633 1.30968163265e-05 662.945918367 1.32183673469e-05 678.537755102 1.33215510204e-05 694.129591837 1.33839183673e-05 709.721428571 1.34925714286e-05 725.313265306 1.36086530612e-05 740.905102041 1.36710204082e-05 756.496938776 1.37333877551e-05 772.08877551 1.3795755102e-05 787.680612245 1.3916244898e-05 803.27244898 1.40409795918e-05 818.864285714 1.41657142857e-05 834.456122449 1.42904489796e-05 850.047959184 1.44151836735e-05 865.639795918 1.45399183673e-05 881.231632653 1.46969795918e-05 896.823469388 1.48840816327e-05 912.415306122 1.50711836735e-05 928.007142857 1.52582857143e-05 943.598979592 1.54453877551e-05 959.190816327 1.57208163265e-05 974.782653061 1.60326530612e-05 990.374489796 1.63444897959e-05 1005.96632653 1.66875918367e-05 1021.55816327 1.70617959184e-05 1037.15 1.7548e-05</interpolate>
      </value>
    </alpha>

  </material>
</materials>
